[
  {
    "id": "beverage_e243dd30ad3c",
    "name": "IPA Delight",
    "slug": "ipa-delight",
    "beverage_type": "Beer",
    "beverage_subtype": "American IPA",
    "declared_style": "American IPA",
    "producer_id": "producer_839628b6f98f",
    "abv": 6.5,
    "ibu": 65,
    "source_beer_id": "BE-001",
    "source_brewery_id": "BR-001",
    "style_match_status": "matched",
    "style_match_method": "exact-name",
    "bjcp_style_id": "bjcp-21a-american-ipa",
    "bjcp_style_name": "American IPA",
    "ba_style_id": "ba-american-ipa",
    "ba_style_name": "American-Style India Pale Ale",
    "style_match_confidence": "exact"
  },
  {
    "id": "beverage_1fd10e726504",
    "name": "Golden Wheat",
    "slug": "golden-wheat",
    "beverage_type": "Beer",
    "beverage_subtype": "Belgian Witbier",
    "declared_style": "Belgian Witbier",
    "producer_id": "producer_13ddd38418d5",
    "abv": 5.2,
    "ibu": 18,
    "source_beer_id": "BE-002",
    "source_brewery_id": "BR-002",
    "style_match_status": "matched",
    "style_match_method": "exact-name",
    "bjcp_style_id": "bjcp-24a-witbier",
    "bjcp_style_name": "Witbier",
    "ba_style_id": "ba-wheat-ale",
    "ba_style_name": "Belgian-Style Witbier",
    "style_match_confidence": "exact"
  },
  {
    "id": "beverage_419b6ee0905e",
    "name": "Dark Stout",
    "slug": "dark-stout",
    "beverage_type": "Beer",
    "beverage_subtype": "Imperial Stout",
    "declared_style": "Imperial Stout",
    "producer_id": "producer_4a6e86e3dc6c",
    "abv": 9.5,
    "ibu": 75,
    "source_beer_id": "BE-003",
    "source_brewery_id": "BR-003",
    "style_match_status": "matched",
    "style_match_method": "exact-name",
    "bjcp_style_id": "bjcp-20c-imperial-stout",
    "bjcp_style_name": "Imperial Stout",
    "ba_style_id": "ba-imperial-stout",
    "ba_style_name": "American-Style Imperial Stout",
    "style_match_confidence": "exact"
  },
  {
    "id": "beverage_c9976d57ce71",
    "name": "Crisp Kölsch",
    "slug": "crisp-kolsch",
    "beverage_type": "Beer",
    "beverage_subtype": "Kölsch",
    "declared_style": "Kölsch",
    "producer_id": "producer_13ddd38418d5",
    "abv": 4.9,
    "ibu": 25,
    "source_beer_id": "BE-004",
    "source_brewery_id": "BR-002",
    "style_match_status": "matched",
    "style_match_method": "exact-name",
    "bjcp_style_id": "bjcp-5b-kolsch",
    "bjcp_style_name": "Kölsch",
    "ba_style_id": "ba-kolsch",
    "ba_style_name": "German-Style Kölsch",
    "style_match_confidence": "exact"
  },
  {
    "id": "beverage_c900689a64cb",
    "name": "Amber Sunset",
    "slug": "amber-sunset",
    "beverage_type": "Beer",
    "beverage_subtype": "American Amber Ale",
    "declared_style": "American Amber Ale",
    "producer_id": "producer_632ea7b04df8",
    "abv": 5.6,
    "ibu": 35,
    "source_beer_id": "BE-005",
    "source_brewery_id": "BR-004",
    "style_match_status": "matched",
    "style_match_method": "exact-name",
    "bjcp_style_id": "bjcp-19a-american-amber-ale",
    "bjcp_style_name": "American Amber Ale",
    "ba_style_id": "ba-american-amber-ale",
    "ba_style_name": "American-Style Amber/Red Ale",
    "style_match_confidence": "exact"
  }
]
